{
  "id": 22,
  "number": 22,
  "name": "贲",
  "name_pinyin": "bi",
  "nature": "山火贲",
  "upper_trigram": "艮",
  "lower_trigram": "离",
  "upper_symbol": "☶",
  "lower_symbol": "☲",
  "full_symbol": "䷕",
  "element": "土",
  "wuxing": {
    "upper": "土",
    "lower": "火"
  },
  "judgment": {
    "text": "贲。亨。小利有攸往。",
    "vernacular": "贲卦象征文饰装饰。亨通。小事前往有利。注重文饰美化,但不要舍本逐末。"
  },
  "image": {
    "text": "山下有火,贲。君子以明庶政,无敢折狱。",
    "vernacular": "山下有火,光辉灿烂,这就是贲卦的卦象。君子观此卦象,应当明察各种政事,但不敢随意断狱。"
  },
  "lines": [
    {
      "position": 1,
      "text": "初九:贲其趾,舍车而徒。",
      "vernacular": "装饰自己的脚,舍弃车辆而步行。注重细节,不慕奢华,脚踏实地。"
    },
    {
      "position": 2,
      "text": "六二:贲其须。",
      "vernacular": "装饰自己的胡须。随波逐流,依附他人,缺乏主见。要有独立人格。"
    },
    {
      "position": 3,
      "text": "九三:贲如濡如,永贞吉。",
      "vernacular": "文饰得光润华美,长久守正吉祥。内外兼修,德才兼备,才能长久。"
    },
    {
      "position": 4,
      "text": "六四:贲如皤如,白马翰如,匪寇,婚媾。",
      "vernacular": "文饰得洁白纯净,白马飞驰,来者不是强盗,是求婚者。纯洁真诚,终成美满姻缘。"
    },
    {
      "position": 5,
      "text": "六五:贲于丘园,束帛戋戋,吝,终吉。",
      "vernacular": "在丘园中装饰,礼物很微薄,有困难,但最终吉祥。质朴简约,虽不华丽但真心诚意。"
    },
    {
      "position": 6,
      "text": "上九:白贲,无咎。",
      "vernacular": "用白色装饰,没有灾咎。返璞归真,朴素自然,是最高境界。"
    }
  ],
  "interpretation_hints": {
    "fortune": "运势平稳,适合修饰完善,但不要过度。注重形式美化,但更要注重内在修养。不要本末倒置",
    "career": "事业要注重包装和形象,但更要注重实质内容。外表很重要,但能力更重要。内外兼修,德才兼备",
    "relationship": "感情要注重仪式感和浪漫,但更要注重真心实意。外表美化很好,但真诚相待更重要。不要只看外表",
    "health": "注重外表形象,适当保养。但不要过度注重外表而忽视内在健康。内外兼顾,才能真正健康",
    "advice": "贲卦提醒我们要注重文饰美化,但不要舍本逐末。形式很重要,但内容更重要。外表装饰要适度,过犹不及。最高境界是返璞归真,质朴自然。内外兼修,德才兼备,才是长久之道"
  },
  "keywords": ["文饰", "装饰", "美化", "适度", "内外", "质朴", "修饰"]
}
