{
  "id": 53,
  "number": 53,
  "name": "渐",
  "name_pinyin": "jian",
  "nature": "风山渐",
  "upper_trigram": "巽",
  "lower_trigram": "艮",
  "upper_symbol": "☴",
  "lower_symbol": "☶",
  "full_symbol": "䷴",
  "element": "木",
  "wuxing": {
    "upper": "木",
    "lower": "土"
  },
  "judgment": {
    "text": "渐。女归吉,利贞。",
    "vernacular": "渐卦象征渐进。女子出嫁吉祥,利于守正。循序渐进,按部就班,终会成功。"
  },
  "image": {
    "text": "山上有木,渐。君子以居贤德善俗。",
    "vernacular": "山上有树木,渐渐生长,这就是渐卦的卦象。君子观此卦象,应当居于贤德,改善风俗。"
  },
  "lines": [
    {
      "position": 1,
      "text": "初六:鸿渐于干,小子厉,有言,无咎。",
      "vernacular": "鸿雁渐进到岸边,小孩子有危险,虽有言语,但没有灾咎。初始阶段,要小心谨慎。"
    },
    {
      "position": 2,
      "text": "六二:鸿渐于磐,饮食衎衎,吉。",
      "vernacular": "鸿雁渐进到磐石,饮食快乐,吉祥。找到稳固的位置,安定下来,生活愉快。"
    },
    {
      "position": 3,
      "text": "九三:鸿渐于陆,夫征不复,妇孕不育,凶。利御寇。",
      "vernacular": "鸿雁渐进到陆地,丈夫出征不回,妇人怀孕不育,凶险。但利于抵御盗寇。过于冒进,会有问题。"
    },
    {
      "position": 4,
      "text": "六四:鸿渐于木,或得其桷,无咎。",
      "vernacular": "鸿雁渐进到树木,或许能找到平坦的树枝,没有灾咎。灵活应变,寻找合适的位置。"
    },
    {
      "position": 5,
      "text": "九五:鸿渐于陵,妇三岁不孕,终莫之胜,吉。",
      "vernacular": "鸿雁渐进到山陵,妇人三年不怀孕,最终没有人能胜过,吉祥。经历磨难,最终成功。"
    },
    {
      "position": 6,
      "text": "上九:鸿渐于陆,其羽可用为仪,吉。",
      "vernacular": "鸿雁渐进到高处,它的羽毛可以用作仪式,吉祥。达到理想境界,成为榜样。"
    }
  ],
  "interpretation_hints": {
    "fortune": "运势需要循序渐进,不要急于求成。像鸿雁南飞一样,一步一步前进。耐心等待,终会成功",
    "career": "事业要稳扎稳打,按部就班。不要冒进,要打好基础。经历时间考验,逐步提升",
    "relationship": "感情要慢慢培养,循序渐进。像女子出嫁一样,要经过正式的程序。不要操之过急,水到渠成",
    "health": "健康要长期调养,不要急于求成。养成良好习惯,持之以恒。注意肝胆和消化系统健康",
    "advice": "渐卦讲的是渐进之道。要循序渐进,按部就班,不要急于求成。像鸿雁南飞,一站一站前进,最终到达目的地。像树木在山上生长,慢慢积累,终成大树。居于贤德,改善风俗,潜移默化地影响他人。耐心等待,终会成功"
  },
  "keywords": ["渐进", "循序", "稳步", "耐心", "积累", "成长", "出嫁"]
}
